metalcore_backend.cpython-311-darwin.so
metalcore/__init__.py
metalcore/activations.py
metalcore/cholesky.py
metalcore/comfy_patch.py
metalcore/config.py
metalcore/eigh.py
metalcore/householder.py
metalcore/lstsq.py
metalcore/ops.py
metalcore/optim.py
metalcore/overrides.py
metalcore/pinv.py
metalcore/qr.py
metalcore/rmsnorm.py
metalcore/sdpa.py
metalcore/solve.py
metalcore/svd.py
metalcore/trsm.py
metalcore/__pycache__/__init__.cpython-310.pyc
metalcore/__pycache__/__init__.cpython-311.pyc
metalcore/__pycache__/__init__.cpython-312.pyc
metalcore/__pycache__/__init__.cpython-313.pyc
metalcore/__pycache__/__init__.cpython-314.pyc
metalcore/__pycache__/__init__.cpython-39.pyc
metalcore/__pycache__/activations.cpython-310.pyc
metalcore/__pycache__/activations.cpython-311.pyc
metalcore/__pycache__/activations.cpython-312.pyc
metalcore/__pycache__/activations.cpython-313.pyc
metalcore/__pycache__/activations.cpython-314.pyc
metalcore/__pycache__/activations.cpython-39.pyc
metalcore/__pycache__/cholesky.cpython-310.pyc
metalcore/__pycache__/cholesky.cpython-311.pyc
metalcore/__pycache__/cholesky.cpython-312.pyc
metalcore/__pycache__/cholesky.cpython-313.pyc
metalcore/__pycache__/cholesky.cpython-314.pyc
metalcore/__pycache__/cholesky.cpython-39.pyc
metalcore/__pycache__/comfy_patch.cpython-310.pyc
metalcore/__pycache__/comfy_patch.cpython-311.pyc
metalcore/__pycache__/comfy_patch.cpython-312.pyc
metalcore/__pycache__/comfy_patch.cpython-313.pyc
metalcore/__pycache__/comfy_patch.cpython-314.pyc
metalcore/__pycache__/comfy_patch.cpython-39.pyc
metalcore/__pycache__/config.cpython-310.pyc
metalcore/__pycache__/config.cpython-311.pyc
metalcore/__pycache__/config.cpython-312.pyc
metalcore/__pycache__/config.cpython-313.pyc
metalcore/__pycache__/config.cpython-314.pyc
metalcore/__pycache__/config.cpython-39.pyc
metalcore/__pycache__/eigh.cpython-310.pyc
metalcore/__pycache__/eigh.cpython-311.pyc
metalcore/__pycache__/eigh.cpython-312.pyc
metalcore-0.1.13.dist-info/licenses/LICENSE
metalcore-0.1.13.dist-info/METADATA
metalcore-0.1.13.dist-info/WHEEL
metalcore-0.1.13.dist-info/top_level.txt
metalcore-0.1.13.dist-info/RECORD
