Metadata-Version: 2.4
Name: metalcore
Version: 0.1.13
Summary: Foundational Metal Linear Algebra Primitives for PyTorch
Author: Kris Bailey
Author-email: Kris Bailey <kris@krisbailey.com>
License: MIT
Project-URL: Homepage, https://github.com/myfykris/metalops
Project-URL: Bug Tracker, https://github.com/myfykris/metalops/issues
Classifier: Development Status :: 3 - Alpha
Classifier: Intended Audience :: Developers
Classifier: Intended Audience :: Science/Research
Classifier: License :: OSI Approved :: MIT License
Classifier: Programming Language :: Python :: 3
Classifier: Programming Language :: Python :: 3.9
Classifier: Programming Language :: Python :: 3.10
Classifier: Programming Language :: Python :: 3.11
Classifier: Programming Language :: Python :: 3.12
Classifier: Programming Language :: Python :: 3.13
Classifier: Programming Language :: Python :: 3.14
Classifier: Programming Language :: C++
Classifier: Topic :: Scientific/Engineering :: Artificial Intelligence
Classifier: Topic :: Scientific/Engineering :: Mathematics
Classifier: Operating System :: MacOS :: MacOS X
Requires-Python: >=3.9
Requires-Dist: torch>=2.0
Requires-Dist: numpy
Dynamic: author
